{
    "AX": {
        "error": 0.06029767256496326, 
        "fit": "average_SEM", 
        "value": -0.011465918382358116
    }, 
    "CDD": {
        "error": 0.00016372067035795029, 
        "fit": "average_SEM", 
        "value": 0.0001839720961773613
    }, 
    "H1": {
        "error": 0.12141766470088408, 
        "fit": "average_SEM", 
        "value": -0.0004489403418119764
    }, 
    "H2": {
        "error": 0.109833698940782, 
        "fit": "average_SEM", 
        "value": 0.01072871897680064
    }, 
    "L1": {
        "error": 0.15131034650841063, 
        "fit": "average_SEM", 
        "value": -0.05013216584532832
    }, 
    "L2": {
        "error": 0.13934976328692622, 
        "fit": "average_SEM", 
        "value": 0.015825275644116725
    }
}