{
    "AX": {
        "error": 0.05896470420586777, 
        "fit": "average_SEM", 
        "value": -0.017858091520611196
    }, 
    "CDD": {
        "error": 0.00016186472693251018, 
        "fit": "average_SEM", 
        "value": 0.0001567649553180672
    }, 
    "H1": {
        "error": 0.11547529624852658, 
        "fit": "average_SEM", 
        "value": 0.0006746371276676655
    }, 
    "H2": {
        "error": 0.12740996138073588, 
        "fit": "average_SEM", 
        "value": -0.008949850148443754
    }, 
    "L1": {
        "error": 0.1683971679900369, 
        "fit": "average_SEM", 
        "value": -0.05722751168359537
    }, 
    "L2": {
        "error": 0.15297890240614384, 
        "fit": "average_SEM", 
        "value": 0.02210113955710161
    }
}