{
    "Ar36": {
        "error": 0.0017990972803203454, 
        "fit": "parabolic", 
        "value": 0.015667530600059834
    }, 
    "Ar37": {
        "error": 0.13959520174830237, 
        "fit": "linear", 
        "value": 0.56225577175962338
    }, 
    "Ar38": {
        "error": 0.18092195914865306, 
        "fit": "linear", 
        "value": 2.3952698733895521
    }, 
    "Ar39": {
        "error": 0.13692525136946507, 
        "fit": "parabolic", 
        "value": 198.76978234224779
    }, 
    "Ar40": {
        "error": 0.50083130449734292, 
        "fit": "parabolic", 
        "value": 1666.4583268814295
    }, 
    "Ar41": {
        "error": 0.12336815830251915, 
        "fit": "average_SEM", 
        "value": 0.034989628511480984
    }
}