{
    "Ar36": {
        "error": 0.0020341381044535361, 
        "fit": "parabolic", 
        "value": 0.0228806776841625
    }, 
    "Ar37": {
        "error": 0.13821902004125353, 
        "fit": "linear", 
        "value": 0.1598650826067175
    }, 
    "Ar38": {
        "error": 0.20685690649926625, 
        "fit": "linear", 
        "value": 0.71917024753177983
    }, 
    "Ar39": {
        "error": 0.091123190449367994, 
        "fit": "parabolic", 
        "value": 64.605091779971971
    }, 
    "Ar40": {
        "error": 0.29588388850924918, 
        "fit": "parabolic", 
        "value": 538.64047415526591
    }, 
    "Ar41": {
        "error": 0.12587864872975979, 
        "fit": "average_SEM", 
        "value": 0.25408023678814062
    }
}