{
    "Ar36": {
        "error": 0.0016800083144454209, 
        "fit": "parabolic", 
        "value": 0.0088372827783045338
    }, 
    "Ar37": {
        "error": 0.13162486750640465, 
        "fit": "linear", 
        "value": 0.54664146263616709
    }, 
    "Ar38": {
        "error": 0.20021352809250098, 
        "fit": "linear", 
        "value": 2.813523682238011
    }, 
    "Ar39": {
        "error": 0.15271208415046739, 
        "fit": "parabolic", 
        "value": 232.21656492326093
    }, 
    "Ar40": {
        "error": 0.58499431862711315, 
        "fit": "parabolic", 
        "value": 1931.3540798588283
    }, 
    "Ar41": {
        "error": 0.1194324706901515, 
        "fit": "average_SEM", 
        "value": 0.035606622959021478
    }
}