{
    "Ar36": {
        "error": 0.001996405230924635, 
        "fit": "parabolic", 
        "value": 0.019993921197688676
    }, 
    "Ar37": {
        "error": 0.13598730540028456, 
        "fit": "linear", 
        "value": 0.62104299544337049
    }, 
    "Ar38": {
        "error": 0.16398297179934709, 
        "fit": "linear", 
        "value": 2.5564862872382035
    }, 
    "Ar39": {
        "error": 0.13891764636134543, 
        "fit": "parabolic", 
        "value": 209.57278382014914
    }, 
    "Ar40": {
        "error": 0.55938715893326096, 
        "fit": "parabolic", 
        "value": 1758.1496232315781
    }, 
    "Ar41": {
        "error": 0.13804804634165285, 
        "fit": "average_SEM", 
        "value": 0.28233626059442757
    }
}