{
    "Ar36": {
        "error": 0.0012984507149932972, 
        "fit": "parabolic", 
        "value": 0.0065351666642143305
    }, 
    "Ar37": {
        "error": 0.13511776381263094, 
        "fit": "linear", 
        "value": 0.2366213241085538
    }, 
    "Ar38": {
        "error": 0.18930063949906833, 
        "fit": "linear", 
        "value": 1.164567762715029
    }, 
    "Ar39": {
        "error": 0.10705988848814904, 
        "fit": "parabolic", 
        "value": 100.18829364044996
    }, 
    "Ar40": {
        "error": 0.37833384151020422, 
        "fit": "parabolic", 
        "value": 846.51979182526657
    }, 
    "Ar41": {
        "error": 0.12160394550203812, 
        "fit": "average_SEM", 
        "value": 0.0091914409381615766
    }
}