{
    "Ar36": {
        "error": 0.001627383356738321, 
        "fit": "parabolic", 
        "value": 0.0077934076512251749
    }, 
    "Ar37": {
        "error": 0.14341415072007441, 
        "fit": "linear", 
        "value": 0.10069726519010724
    }, 
    "Ar38": {
        "error": 0.19504608823486894, 
        "fit": "linear", 
        "value": 1.0346226118804447
    }, 
    "Ar39": {
        "error": 0.10035304068984939, 
        "fit": "parabolic", 
        "value": 92.278882395338769
    }, 
    "Ar40": {
        "error": 0.34619661162894338, 
        "fit": "parabolic", 
        "value": 779.17955641488072
    }, 
    "Ar41": {
        "error": 0.11695672992493002, 
        "fit": "average_SEM", 
        "value": -0.039775984985753896
    }
}