{
    "Ar36": {
        "error": 0.0021620432932480771, 
        "fit": "parabolic", 
        "value": 0.022665812748956078
    }, 
    "Ar37": {
        "error": 0.13566075392958499, 
        "fit": "linear", 
        "value": 0.34995496421777894
    }, 
    "Ar38": {
        "error": 0.21339456886345026, 
        "fit": "linear", 
        "value": 2.2564607957663054
    }, 
    "Ar39": {
        "error": 0.12599610904389946, 
        "fit": "parabolic", 
        "value": 191.45176936632257
    }, 
    "Ar40": {
        "error": 0.5037193886725152, 
        "fit": "parabolic", 
        "value": 1615.9261646758364
    }, 
    "Ar41": {
        "error": 0.12281681652089488, 
        "fit": "average_SEM", 
        "value": -0.0080140232663688943
    }
}