{
    "AX": {
        "error": 0.05077920748808246, 
        "fit": "average_SEM", 
        "value": -0.007035487340181135
    }, 
    "CDD": {
        "error": 0.0001100181001219294, 
        "fit": "average_SEM", 
        "value": 6.866564047716869e-05
    }, 
    "H1": {
        "error": 0.12211036625825211, 
        "fit": "average_SEM", 
        "value": -0.018395286338879182
    }, 
    "H2": {
        "error": 0.130679011815811, 
        "fit": "average_SEM", 
        "value": -0.005007818874825413
    }, 
    "L1": {
        "error": 0.13439612130059084, 
        "fit": "average_SEM", 
        "value": -0.03831305199467654
    }, 
    "L2": {
        "error": 0.12241802989180918, 
        "fit": "average_SEM", 
        "value": 0.002824076138009938
    }
}