{
    "AX": {
        "error": 0.06205981529228526, 
        "fit": "average_SEM", 
        "value": -0.01315247649132895
    }, 
    "CDD": {
        "error": 0.00012148957081915967, 
        "fit": "average_SEM", 
        "value": 0.00010364625001481423
    }, 
    "H1": {
        "error": 0.11943581676775632, 
        "fit": "average_SEM", 
        "value": -0.020036856882211396
    }, 
    "H2": {
        "error": 0.14584457950870136, 
        "fit": "average_SEM", 
        "value": 0.2833531777374446
    }, 
    "L1": {
        "error": 0.1230617438298692, 
        "fit": "average_SEM", 
        "value": -0.03734786516288295
    }, 
    "L2": {
        "error": 0.13331566512644497, 
        "fit": "average_SEM", 
        "value": -0.1402161284951338
    }
}