{
    "AX": {
        "error": 0.05388665525381666, 
        "fit": "average_SEM", 
        "value": 0.0020036782831690894
    }, 
    "CDD": {
        "error": 9.16173654596574e-05, 
        "fit": "average_SEM", 
        "value": 6.607448376598768e-05
    }, 
    "H1": {
        "error": 0.1160064577993579, 
        "fit": "average_SEM", 
        "value": -0.014568897722832238
    }, 
    "H2": {
        "error": 0.1527900735919309, 
        "fit": "average_SEM", 
        "value": 0.011878521056981601
    }, 
    "L1": {
        "error": 0.1343318172295912, 
        "fit": "average_SEM", 
        "value": -0.04313606522822132
    }, 
    "L2": {
        "error": 0.13033341491324543, 
        "fit": "average_SEM", 
        "value": -0.10778968083395739
    }
}