{
    "AX": {
        "error": 0.05328658967422381, 
        "fit": "average_SEM", 
        "value": -0.0060580889117166714
    }, 
    "CDD": {
        "error": 0.00011889127777659018, 
        "fit": "average_SEM", 
        "value": 9.975951519057465e-05
    }, 
    "H1": {
        "error": 0.14837883532886276, 
        "fit": "average_SEM", 
        "value": -0.0022178019125324985
    }, 
    "H2": {
        "error": 0.14020808548360092, 
        "fit": "average_SEM", 
        "value": 0.006117575887280206
    }, 
    "L1": {
        "error": 0.1391470564619668, 
        "fit": "average_SEM", 
        "value": -0.04989425106008032
    }, 
    "L2": {
        "error": 0.13640356721122976, 
        "fit": "average_SEM", 
        "value": -0.09420666272829598
    }
}