{
    "AX": {
        "error": 0.06440412470581218, 
        "fit": "average_SEM", 
        "value": -0.005206233264956003
    }, 
    "CDD": {
        "error": 0.00012472747688996137, 
        "fit": "average_SEM", 
        "value": 0.0001256710776942782
    }, 
    "H1": {
        "error": 0.1343987009847531, 
        "fit": "average_SEM", 
        "value": -0.022645884536905213
    }, 
    "H2": {
        "error": 0.12778305678130164, 
        "fit": "average_SEM", 
        "value": -0.005968843918769077
    }, 
    "L1": {
        "error": 0.1316172079158494, 
        "fit": "average_SEM", 
        "value": -0.04864519675805544
    }, 
    "L2": {
        "error": 0.13683461832360774, 
        "fit": "average_SEM", 
        "value": -0.10729248958911436
    }
}