{
    "AX": {
        "error": 0.055808925490835735, 
        "fit": "average_SEM", 
        "value": -0.0036491736871236452
    }, 
    "CDD": {
        "error": 0.000145753811790393, 
        "fit": "average_SEM", 
        "value": 0.00012567107817934204
    }, 
    "H1": {
        "error": 0.12145660249974262, 
        "fit": "average_SEM", 
        "value": -0.03561078612741161
    }, 
    "H2": {
        "error": 0.13191804663778772, 
        "fit": "average_SEM", 
        "value": 0.25961935026571153
    }, 
    "L1": {
        "error": 0.14336389763000562, 
        "fit": "average_SEM", 
        "value": -0.05280754933725499
    }, 
    "L2": {
        "error": 0.13193647826190305, 
        "fit": "average_SEM", 
        "value": -0.08319076636932247
    }
}