{
    "AX": {
        "error": 0.0572351147626537, 
        "fit": "average_SEM", 
        "value": -0.008751143640741551
    }, 
    "CDD": {
        "error": 0.00015001727242384516, 
        "fit": "average_SEM", 
        "value": 0.00017101631359158395
    }, 
    "H1": {
        "error": 0.12704429042099377, 
        "fit": "average_SEM", 
        "value": -0.03220296167613317
    }, 
    "H2": {
        "error": 0.13854212456409115, 
        "fit": "average_SEM", 
        "value": 0.27605365866523546
    }, 
    "L1": {
        "error": 0.12992017595415475, 
        "fit": "average_SEM", 
        "value": -0.03692501216307088
    }, 
    "L2": {
        "error": 0.12789053940341968, 
        "fit": "average_SEM", 
        "value": -0.09141928063951733
    }
}