{
    "Ar36": {
        "error": 0.0021072055041375499, 
        "fit": "parabolic", 
        "value": 0.022362328495479398
    }, 
    "Ar37": {
        "error": 0.14437154541350106, 
        "fit": "linear", 
        "value": 0.66612782340378285
    }, 
    "Ar38": {
        "error": 0.16346509427884331, 
        "fit": "linear", 
        "value": 2.4379181646855859
    }, 
    "Ar39": {
        "error": 0.14407369604331138, 
        "fit": "parabolic", 
        "value": 203.88977849399416
    }, 
    "Ar40": {
        "error": 0.47472743813381951, 
        "fit": "parabolic", 
        "value": 1696.9085693588722
    }, 
    "Ar41": {
        "error": 0.18852766286046416, 
        "fit": "average_SEM", 
        "value": 0.16357151590427385
    }
}