{
    "Ar36": {
        "error": 0.0043688148492705215, 
        "fit": "parabolic", 
        "value": 0.10847287294824048
    }, 
    "Ar37": {
        "error": 0.14733923106417987, 
        "fit": "linear", 
        "value": 1.0711559930872547
    }, 
    "Ar38": {
        "error": 0.14066616201207993, 
        "fit": "linear", 
        "value": 3.5831556826100703
    }, 
    "Ar39": {
        "error": 0.17378511554715079, 
        "fit": "parabolic", 
        "value": 290.18033713360694
    }, 
    "Ar40": {
        "error": 0.59682365186199759, 
        "fit": "parabolic", 
        "value": 2435.0307243155466
    }, 
    "Ar41": {
        "error": 0.13486872310860593, 
        "fit": "average_SEM", 
        "value": 0.27020485813170669
    }
}