{
    "AX": {
        "error": 0.05692600737001758, 
        "fit": "average_SEM", 
        "value": 0.00039807991167132667
    }, 
    "CDD": {
        "error": 4.6836371888270304e-05, 
        "fit": "average_SEM", 
        "value": 1.5546937356702982e-05
    }, 
    "H1": {
        "error": 0.1431533778918969, 
        "fit": "average_SEM", 
        "value": -0.05267800953006372
    }, 
    "H2": {
        "error": 0.14796633630654338, 
        "fit": "average_SEM", 
        "value": -0.020799569921412814
    }, 
    "L1": {
        "error": 0.13492827998880208, 
        "fit": "average_SEM", 
        "value": -0.03547006838925881
    }, 
    "L2": {
        "error": 0.13476072902095182, 
        "fit": "average_SEM", 
        "value": -0.11383666410498942
    }
}