{
    "AX": {
        "error": 0.05632037611077137, 
        "fit": "average_SEM", 
        "value": -0.015485300667448125
    }, 
    "CDD": {
        "error": 0.00015814101187315422, 
        "fit": "average_SEM", 
        "value": 0.00013603570526659798
    }, 
    "H1": {
        "error": 0.12692461164292143, 
        "fit": "average_SEM", 
        "value": -0.026410023336453984
    }, 
    "H2": {
        "error": 0.14247661646057283, 
        "fit": "average_SEM", 
        "value": -0.004941574843299653
    }, 
    "L1": {
        "error": 0.10759211380114578, 
        "fit": "average_SEM", 
        "value": -0.024407960833438363
    }, 
    "L2": {
        "error": 0.13742636406863887, 
        "fit": "average_SEM", 
        "value": -0.0902366337919375
    }
}