{
    "Ar36": {
        "error": 0.0014712097655681579, 
        "fit": "parabolic", 
        "value": 0.0054324445702442613
    }, 
    "Ar37": {
        "error": 0.13370606364719434, 
        "fit": "linear", 
        "value": 0.85733706705260604
    }, 
    "Ar38": {
        "error": 0.12915227594006182, 
        "fit": "linear", 
        "value": 2.7866414390167185
    }, 
    "Ar39": {
        "error": 0.15542023147377973, 
        "fit": "parabolic", 
        "value": 229.53043144858407
    }, 
    "Ar40": {
        "error": 0.57314386307968879, 
        "fit": "parabolic", 
        "value": 1902.3573739325159
    }, 
    "Ar41": {
        "error": 0.13081474093230136, 
        "fit": "average_SEM", 
        "value": 0.023014422816224397
    }
}