{
    "Ar36": {
        "error": 0.0011054123339869185, 
        "fit": "parabolic", 
        "value": 0.0040988866254630472
    }, 
    "Ar37": {
        "error": 0.13185220171772974, 
        "fit": "linear", 
        "value": -0.10872158670852883
    }, 
    "Ar38": {
        "error": 0.12597039399100193, 
        "fit": "linear", 
        "value": -0.044161756410757369
    }, 
    "Ar39": {
        "error": 0.010971305565335938, 
        "fit": "parabolic", 
        "value": 0.022200332211039779
    }, 
    "Ar40": {
        "error": 0.14348859509277093, 
        "fit": "parabolic", 
        "value": 1.1614166809628936
    }, 
    "Ar41": {
        "error": 0.1275706872758457, 
        "fit": "average_SEM", 
        "value": 0.25086457785388727
    }
}